sphinx_compas_theme/__init__.py
sphinx_compas_theme/compas/genindex.html
sphinx_compas_theme/compas/layout.html
sphinx_compas_theme/compas/search.html
sphinx_compas_theme/compas/searchresults.html
sphinx_compas_theme/compas/theme.conf
sphinx_compas_theme/compas/static/PLACEHOLDER
sphinx_compas_theme/compaspkg/genindex.html
sphinx_compas_theme/compaspkg/layout.html
sphinx_compas_theme/compaspkg/search.html
sphinx_compas_theme/compaspkg/searchresults.html
sphinx_compas_theme/compaspkg/theme.conf
sphinx_compas_theme/compaspkg/static/PLACEHOLDER
sphinx_compas_theme/ext/tabs.py
sphinx_compas_theme/shared/static/css/compas-reference.css
sphinx_compas_theme/shared/static/css/compas-reference.css.map
sphinx_compas_theme/shared/static/css/compas-reference.scss
sphinx_compas_theme/shared/static/css/compas.css
sphinx_compas_theme/shared/static/css/bootstrap-scss/_alert.scss
sphinx_compas_theme/shared/static/css/bootstrap-scss/_badge.scss
sphinx_compas_theme/shared/static/css/bootstrap-scss/_breadcrumb.scss
sphinx_compas_theme/shared/static/css/bootstrap-scss/_button-group.scss
sphinx_compas_theme/shared/static/css/bootstrap-scss/_buttons.scss
sphinx_compas_theme/shared/static/css/bootstrap-scss/_card.scss
sphinx_compas_theme/shared/static/css/bootstrap-scss/_carousel.scss
sphinx_compas_theme/shared/static/css/bootstrap-scss/_close.scss
sphinx_compas_theme/shared/static/css/bootstrap-scss/_code.scss
sphinx_compas_theme/shared/static/css/bootstrap-scss/_custom-forms.scss
sphinx_compas_theme/shared/static/css/bootstrap-scss/_dropdown.scss
sphinx_compas_theme/shared/static/css/bootstrap-scss/_forms.scss
sphinx_compas_theme/shared/static/css/bootstrap-scss/_functions.scss
sphinx_compas_theme/shared/static/css/bootstrap-scss/_grid.scss
sphinx_compas_theme/shared/static/css/bootstrap-scss/_images.scss
sphinx_compas_theme/shared/static/css/bootstrap-scss/_input-group.scss
sphinx_compas_theme/shared/static/css/bootstrap-scss/_jumbotron.scss
sphinx_compas_theme-0.15.18.dist-info/AUTHORS.md
sphinx_compas_theme-0.15.18.dist-info/LICENSE
sphinx_compas_theme-0.15.18.dist-info/METADATA
sphinx_compas_theme-0.15.18.dist-info/WHEEL
sphinx_compas_theme-0.15.18.dist-info/entry_points.txt
sphinx_compas_theme-0.15.18.dist-info/top_level.txt
sphinx_compas_theme-0.15.18.dist-info/RECORD
