Metadata-Version: 2.1
Name: sphinx-compas-theme
Version: 0.15.18
Summary: Sphinx Theme for COMPAS.
Home-page: https://github.com/compas-dev/sphinx_compas_theme
Author: Tom Van Mele
Author-email: van.mele@arch.ethz.ch
License: MIT
Platform: UNKNOWN
Classifier: Development Status :: 4 - Beta
Classifier: Intended Audience :: Developers
Classifier: Topic :: Documentation
Classifier: License :: OSI Approved :: MIT License
Classifier: Operating System :: Unix
Classifier: Operating System :: POSIX
Classifier: Operating System :: Microsoft :: Windows
Classifier: Programming Language :: Python
Classifier: Programming Language :: Python :: 3
Classifier: Programming Language :: Python :: 3.6
Classifier: Programming Language :: Python :: 3.7
Classifier: Programming Language :: Python :: 3.8
Classifier: Programming Language :: Python :: 3.9
Classifier: Programming Language :: Python :: Implementation :: CPython
Requires-Python: >=3.6
License-File: LICENSE
License-File: AUTHORS.md
Requires-Dist: setuptools
Requires-Dist: sphinx (>=1.6)
Requires-Dist: invoke (>=0.14)
Requires-Dist: bumpversion (>=0.5)
Requires-Dist: check-manifest (>=0.36)
Requires-Dist: twine
